sifi_bridge_py-1.2.3.dist-info/METADATA
sifi_bridge_py-1.2.3.dist-info/WHEEL
sifi_bridge_py-1.2.3.dist-info/entry_points.txt
sifi_bridge_py-1.2.3.dist-info/licenses/LICENSE
sifi_bridge_py/__init__.py
sifi_bridge_py/sifi_bridge.py
sifi_bridge_py/utils.py
sifi_bridge_py-1.2.3.dist-info/RECORD
