Metadata-Version: 2.1
Name: sifi-bridge-py
Version: 1.2.3
Summary: Python bindings over the SiFi Bridge tool.
Author-Email: SiFi Labs <gabrielg@sifilabs.com>
License: MIT
Project-URL: repository, https://github.com/SiFiLabs/sifi-bridge-py
Requires-Python: <3.13,>=3.9
Requires-Dist: numpy
Requires-Dist: requests>=2.32.3
Requires-Dist: semantic-version>=2.10.0
Provides-Extra: examples
Requires-Dist: matplotlib>=3.9.2; extra == "examples"
Requires-Dist: pylsl>=1.16.2; extra == "examples"
Requires-Dist: PySide6>=6.7.2; extra == "examples"
Requires-Dist: pyqtgraph>=0.13.7; extra == "examples"
